Workbook

Sheet 1. Resumen ejecutivo
A1: PRESUPUESTO DETALLADO — PROYECTO PreVe
A2: Sistema predictivo de seguridad para juventudes — Hackathon RedPública (PNUD)
A4: Información general
A5: Equipo: | B5: Minsky Devs (5 integrantes — UPC)
A6: Zona del piloto: | B6: Lima Centro (Cercado, Breña, La Victoria)
A7: Duración del piloto: | B7: 60 días (Agosto – Octubre 2026)
A8: Beneficiarios directos: | B8: 500+ estudiantes universitarios
A9: Universidades aliadas previstas: | B9: 2 (en Lima Centro)
A10: Moneda: | B10: Soles peruanos (S/)
A11: Fondo PNUD solicitado: | B11: S/ 10 000,00
A14: Resumen por rubro
A16: N.º | B16: Rubro | C16: Monto (S/) | D16: % del total | E16: Hoja de detalle
A17: 1 | B17: Desarrollo tecnológico | C17: ='2. Desarrollo tecnológico'!F14 -> 3500 | D17: =C17/$C$22 -> 0.35 | E17: Hoja 2
A18: 2 | B18: Materiales y logística de campo | C18: ='3. Materiales y logística'!F12 -> 1800 | D18: =C18/$C$22 -> 0.18 | E18: Hoja 3
A19: 3 | B19: Talleres y activación comunitaria | C19: ='4. Talleres y activación'!F11 -> 2200 | D19: =C19/$C$22 -> 0.22 | E19: Hoja 4
A20: 4 | B20: Comunicación y difusión | C20: ='5. Comunicación y difusión'!F10 -> 1500 | D20: =C20/$C$22 -> 0.15 | E20: Hoja 5
A21: 5 | B21: Monitoreo, evaluación y reportes | C21: ='6. Monitoreo y evaluación'!F11 -> 1000 | D21: =C21/$C$22 -> 0.1 | E21: Hoja 6
B22: TOTAL FONDO PNUD | C22: =SUM(C17:C21) -> 10000 | D22: =C22/10000 -> 1
A25: Notas:
A26: • Todos los montos están expresados en soles peruanos (PEN).
A27: • Servicios cotizados en USD se convierten al tipo de cambio operacional de Naciones Unidas vigente al momento del desembolso.
A28: • El presupuesto se ajusta exactamente al Fondo de Innovación Juvenil del PNUD (S/ 10 000,00).
A29: • Se considera además contrapartida no monetaria del equipo y de universidades aliadas (ver Hoja 8).

Sheet 2. Desarrollo tecnológico
A1: RUBRO 1: DESARROLLO TECNOLÓGICO
A2: Cubre toda la infraestructura técnica necesaria para que la plataforma quede operativa durante el piloto: servidores, mensajería WhatsApp, APIs de mapas y modelos de IA, dominio y herramientas de despliegue.
A4: Ítem | B4: Descripción | C4: Unidad | D4: Cantidad | E4: P. unitario (S/) | F4: Subtotal (S/)
A5: Servidor cloud | B5: Hosting backend + base de datos PostgreSQL (Railway/Render plan inicial) | C5: mes | D5: 3 | E5: 180 | F5: =D5*E5 -> 540
A6: Twilio WhatsApp Business API | B6: Mensajería WhatsApp para chatbot (sesión + plantillas) | C6: mes | D6: 3 | E6: 280 | F6: =D6*E6 -> 840
A7: Dominio web | B7: Registro de dominio .pe por 1 año | C7: año | D7: 1 | E7: 120 | F7: =D7*E7 -> 120
A8: Certificado SSL | B8: Certificado para HTTPS (Let's Encrypt + configuración profesional) | C8: und | D8: 1 | E8: 80 | F8: =D8*E8 -> 80
A9: API Google Maps | B9: Maps JavaScript API + Geocoding para mapa de calor | C9: mes | D9: 3 | E9: 200 | F9: =D9*E9 -> 600
A10: Servicios de IA (OpenAI / Claude API) | B10: Procesamiento NLP para extraer datos del lenguaje natural | C10: mes | D10: 3 | E10: 180 | F10: =D10*E10 -> 540
A11: Herramientas dev y CI/CD | B11: GitHub Pro, Vercel, herramientas de despliegue continuo | C11: mes | D11: 3 | E11: 80 | F11: =D11*E11 -> 240
A12: Suscripción a base de datos pública | B12: Acceso a Datos Abiertos del Estado y backups | C12: und | D12: 1 | E12: 100 | F12: =D12*E12 -> 100
A13: Buffer técnico | B13: Reserva para imprevistos técnicos (errores de cobranza, ajustes de plan, sobre-uso) | C13: und | D13: 1 | E13: 440 | F13: =D13*E13 -> 440
E14: TOTAL DEL RUBRO | F14: =SUM(F5:F13) -> 3500
A17: Supuestos y notas por ítem
A18: • Servidor cloud: | B18: Plan inicial de Railway/Render ≈ USD 12-15/mes incluyendo BD; cubre los 60 días del piloto y un mes de configuración previa.
A19: • Twilio WhatsApp Business API: | B19: Estimado USD 75/mes para ~3 000 mensajes (entrantes + plantillas de alerta). Incluye número de pruebas en sandbox y producción.
A20: • Dominio web: | B20: Costo promedio de un dominio .pe (Punto Pe / NIC.pe) entre S/ 80-150 según renovación.
A21: • Certificado SSL: | B21: Let's Encrypt es gratuito; el monto cubre la configuración inicial profesional con renovación automática.
A22: • API Google Maps: | B22: USD 200 mensuales de crédito gratuito de Google + estimado USD 50/mes adicional según volumen de cargas.
A23: • Servicios de IA (OpenAI / Claude API): | B23: Estimado USD 50/mes para ~5 000 mensajes procesados con modelos ligeros (GPT-4o-mini o Claude Haiku).
A24: • Herramientas dev y CI/CD: | B24: GitHub Pro USD 4/mes por usuario y Vercel plan Hobby gratuito; cubre 3 miembros del equipo en plan Pro.
A25: • Suscripción a base de datos pública: | B25: Almacenamiento adicional en la nube para backups del dataset y datos descargados de DATACRIM/INEI.
A26: • Buffer técnico: | B26: Buffer del ~12% del rubro para cubrir desviaciones cambiarias (USD/PEN) y excesos de cuotas en APIs.

Sheet 3. Materiales y logística
A1: RUBRO 2: MATERIALES Y LOGÍSTICA
A2: Cubre el material físico necesario para la activación territorial del piloto en universidades y paraderos clave de Lima Centro, así como la movilidad del equipo durante los 60 días.
A4: Ítem | B4: Descripción | C4: Unidad | D4: Cantidad | E4: P. unitario (S/) | F4: Subtotal (S/)
A5: Afiches A3 | B5: Afiches informativos con código QR para universidades y paraderos | C5: und | D5: 100 | E5: 3.5 | F5: =D5*E5 -> 350
A6: Stickers con QR | B6: Stickers vinílicos resistentes para fijar en paraderos y zonas estratégicas | C6: und | D6: 200 | E6: 1.2 | F6: =D6*E6 -> 240
A7: Volantes A5 | B7: Volantes de difusión para entregar en activaciones universitarias | C7: und | D7: 500 | E7: 0.3 | F7: =D7*E7 -> 150
A8: Roll-up promocional | B8: Banner para mesas de activación (1 unidad) | C8: und | D8: 2 | E8: 120 | F8: =D8*E8 -> 240
A9: Refrigerios talleres | B9: Refrigerio simple para asistentes a 3 talleres (jugo + sándwich) | C9: ración | D9: 90 | E9: 5 | F9: =D9*E9 -> 450
A10: Movilidad del equipo | B10: Pasajes y viáticos de campo del equipo durante el piloto | C10: viaje | D10: 30 | E10: 10 | F10: =D10*E10 -> 300
A11: Imprevistos logísticos | B11: Reserva para gastos no previstos en logística de campo | C11: und | D11: 1 | E11: 70 | F11: =D11*E11 -> 70
E12: TOTAL DEL RUBRO | F12: =SUM(F5:F11) -> 1800
A15: Supuestos y notas por ítem
A16: • Afiches A3: | B16: Impresión a color en papel couché 150 g; cotización promedio Lima centro S/ 3-4 por unidad para tirajes de 100.
A17: • Stickers con QR: | B17: Stickers vinílicos 10x10 cm; precio promedio S/ 1-1,5 por unidad en imprentas digitales locales.
A18: • Volantes A5: | B18: Tiraje volante A5 a una cara, papel bond 90 g; precio promedio S/ 0,25-0,35 unidad.
A19: • Roll-up promocional: | B19: Roll-up estándar 80x200 cm; cotización promedio S/ 100-140 por unidad incluyendo diseño.
A20: • Refrigerios talleres: | B20: 30 asistentes por taller x 3 talleres = 90 raciones; refrigerio simple S/ 5-7 por persona.
A21: • Movilidad del equipo: | B21: 30 desplazamientos en taxi/Uber/transporte público para coordinaciones, entrega de materiales y visitas de campo.
A22: • Imprevistos logísticos: | B22: Buffer del ~4% del rubro para reposición de material dañado, transporte adicional o materiales menores.

Sheet 4. Talleres y activación
A1: RUBRO 3: TALLERES Y ACTIVACIÓN
A2: Cubre la realización de 3 talleres con la comunidad estudiantil en universidades aliadas y la sesión de cierre con autoridades. Es el rubro clave para asegurar la adopción real de la plataforma.
A4: Ítem | B4: Descripción | C4: Unidad | D4: Cantidad | E4: P. unitario (S/) | F4: Subtotal (S/)
A5: Alquiler de aulas/auditorios | B5: Espacio para 3 talleres en universidades aliadas (caso de no obtener cesión gratuita) | C5: taller | D5: 3 | E5: 150 | F5: =D5*E5 -> 450
A6: Honorarios facilitadores externos | B6: Especialistas invitados en seguridad ciudadana / tecnología (1 por taller) | C6: sesión | D6: 3 | E6: 200 | F6: =D6*E6 -> 600
A7: Material didáctico | B7: Cuadernillos, lapiceros, fichas de registro y stickers para participantes | C7: kit | D7: 90 | E7: 3 | F7: =D7*E7 -> 270
A8: Sorteos e incentivos | B8: Pequeños incentivos para fomentar el registro de usuarios en talleres (cargadores, audífonos básicos) | C8: incentivo | D8: 12 | E8: 20 | F8: =D8*E8 -> 240
A9: Sesión de cierre con autoridades | B9: Evento de cierre con representantes de PNUD, universidades aliadas y municipalidad | C9: evento | D9: 1 | E9: 240 | F9: =D9*E9 -> 240
A10: Diseño de contenidos formativos | B10: Honorarios por diseño pedagógico de los talleres (slides, dinámicas) | C10: consultoría | D10: 1 | E10: 400 | F10: =D10*E10 -> 400
E11: TOTAL DEL RUBRO | F11: =SUM(F5:F10) -> 2200
A14: Supuestos y notas por ítem
A15: • Alquiler de aulas/auditorios: | B15: Alquiler de aula con proyector ≈ S/ 100-200 por sesión de 2 h; se priorizará cesión gratuita por aliados.
A16: • Honorarios facilitadores externos: | B16: Honorarios profesionales para 1 especialista invitado por taller (criminólogo, dev senior, comunicador social).
A17: • Material didáctico: | B17: Kit por participante en los 3 talleres (~30 asistentes c/u); cuadernillo + lapicero + ficha.
A18: • Sorteos e incentivos: | B18: 4 incentivos por taller para participación activa y registros completos; promedio S/ 20 por ítem.
A19: • Sesión de cierre con autoridades: | B19: Sesión presencial de 2 h con coffee break ligero, material de presentación y traslados de invitados.
A20: • Diseño de contenidos formativos: | B20: Diseño profesional de los 3 talleres por consultor externo o reconocimiento al miembro del equipo a cargo.

Sheet 5. Comunicación y difusión
A1: RUBRO 4: COMUNICACIÓN Y DIFUSIÓN
A2: Cubre el desarrollo de la identidad visual del proyecto, la producción de contenidos audiovisuales y la pauta digital orientada específicamente a estudiantes universitarios de Lima Centro.
A4: Ítem | B4: Descripción | C4: Unidad | D4: Cantidad | E4: P. unitario (S/) | F4: Subtotal (S/)
A5: Diseño de identidad visual | B5: Logotipo, paleta, manual de marca y plantillas para redes sociales | C5: consultoría | D5: 1 | E5: 350 | F5: =D5*E5 -> 350
A6: Producción de video institucional | B6: Video corto (1-2 min) sobre el problema y la solución PreVe | C6: und | D6: 1 | E6: 350 | F6: =D6*E6 -> 350
A7: Pauta digital focalizada | B7: Anuncios en Instagram y TikTok dirigidos a jóvenes universitarios de Lima Centro | C7: mes | D7: 2 | E7: 250 | F7: =D7*E7 -> 500
A8: Producción de contenidos para redes | B8: Diseño de 20 piezas para redes sociales durante el piloto | C8: pieza | D8: 20 | E8: 10 | F8: =D8*E8 -> 200
A9: Notas de prensa y difusión | B9: Redacción y distribución a medios universitarios y locales | C9: consultoría | D9: 1 | E9: 100 | F9: =D9*E9 -> 100
E10: TOTAL DEL RUBRO | F10: =SUM(F5:F9) -> 1500
A13: Supuestos y notas por ítem
A14: • Diseño de identidad visual: | B14: Diseño gráfico profesional; rango Lima S/ 300-500 para identidad básica con manual.
A15: • Producción de video institucional: | B15: Producción audiovisual básica con motion graphics; S/ 300-450 según complejidad y duración.
A16: • Pauta digital focalizada: | B16: Pauta digital segmentada por edad (18-29) y zona (Lima Centro); CPM bajo en audiencia local.
A17: • Producción de contenidos para redes: | B17: Costo unitario por pieza editada (post + story); estimación local de community management.
A18: • Notas de prensa y difusión: | B18: Honorario simbólico para redacción profesional de 2-3 notas de prensa y gestión con medios universitarios.

Sheet 6. Monitoreo y evaluación
A1: RUBRO 5: MONITOREO Y EVALUACIÓN
A2: Cubre la evaluación rigurosa del piloto: diseño de instrumentos, aplicación de encuestas, análisis estadístico, elaboración de informes (avance y final) y sistematización de aprendizajes.
A4: Ítem | B4: Descripción | C4: Unidad | D4: Cantidad | E4: P. unitario (S/) | F4: Subtotal (S/)
A5: Diseño de encuestas y formularios | B5: Diseño metodológico de encuestas de línea de base, intermedia y final | C5: consultoría | D5: 1 | E5: 250 | F5: =D5*E5 -> 250
A6: Aplicación y procesamiento de encuestas | B6: Trabajo de campo para aplicar las 3 mediciones a usuarios del piloto | C6: encuesta | D6: 150 | E6: 2 | F6: =D6*E6 -> 300
A7: Análisis estadístico | B7: Análisis cuantitativo de resultados con Python/Power BI | C7: consultoría | D7: 1 | E7: 150 | F7: =D7*E7 -> 150
A8: Elaboración de informe de avance | B8: Informe parcial a los 30 días del piloto | C8: informe | D8: 1 | E8: 100 | F8: =D8*E8 -> 100
A9: Elaboración de informe final | B9: Informe de cierre con resultados, aprendizajes y recomendaciones | C9: informe | D9: 1 | E9: 150 | F9: =D9*E9 -> 150
A10: Sistematización de aprendizajes | B10: Documento de buenas prácticas y casos de uso para replicabilidad | C10: documento | D10: 1 | E10: 50 | F10: =D10*E10 -> 50
E11: TOTAL DEL RUBRO | F11: =SUM(F5:F10) -> 1000
A14: Supuestos y notas por ítem
A15: • Diseño de encuestas y formularios: | B15: Diseño metodológico de 3 instrumentos (KoboToolbox/Google Forms); incluye pretest con 5 usuarios.
A16: • Aplicación y procesamiento de encuestas: | B16: 150 encuestas total (50 por momento de medición); costo simbólico por aplicación y procesamiento.
A17: • Análisis estadístico: | B17: Análisis estadístico de variables del piloto, indicadores clave y elaboración de gráficos para informes.
A18: • Elaboración de informe de avance: | B18: Informe formal a los 30 días con avances, primeras métricas y aprendizajes preliminares para el PNUD.
A19: • Elaboración de informe final: | B19: Informe final completo con metodología, resultados, sistematización de aprendizajes y recomendaciones.
A20: • Sistematización de aprendizajes: | B20: Documento abierto que permita a otras iniciativas replicar la metodología de PreVe en otras zonas.

Sheet 7. Cronograma desembolsos
A1: CRONOGRAMA DE DESEMBOLSOS
A2: El PNUD se reserva el derecho de organizar los desembolsos en dos transferencias. Se propone la siguiente distribución temporal:
A4: Rubro | B4: Mes 1 (S/) | C4: Mes 2 (S/) | D4: Mes 3 (S/) | E4: Total (S/) | F4: % del rubro | G4: Justificación
A5: Desarrollo tecnológico | B5: 2100 | C5: 1000 | D5: 400 | E5: =SUM(B5:D5) -> 3500 | F5: =E5/10000 -> 0.35 | G5: 60% al inicio (infra, licencias anuales). 28% en mes 2 (operación). 12% en mes 3 (cierre).
A6: Materiales y logística | B6: 1200 | C6: 400 | D6: 200 | E6: =SUM(B6:D6) -> 1800 | F6: =E6/10000 -> 0.18 | G6: 67% al inicio para producir todo el material físico antes de los talleres.
A7: Talleres y activación | B7: 800 | C7: 1100 | D7: 300 | E7: =SUM(B7:D7) -> 2200 | F7: =E7/10000 -> 0.22 | G7: Mayor desembolso en mes 2 (talleres principales). Mes 3 para sesión de cierre.
A8: Comunicación y difusión | B8: 700 | C8: 500 | D8: 300 | E8: =SUM(B8:D8) -> 1500 | F8: =E8/10000 -> 0.15 | G8: 47% al inicio para identidad y video. Pauta digital distribuida en meses 2 y 3.
A9: Monitoreo y evaluación | B9: 200 | C9: 400 | D9: 400 | E9: =SUM(B9:D9) -> 1000 | F9: =E9/10000 -> 0.1 | G9: Crece progresivamente: diseño inicial → aplicación intermedia → informe final.
A10: TOTAL POR MES | B10: =SUM(B5:B9) -> 5000 | C10: =SUM(C5:C9) -> 3400 | D10: =SUM(D5:D9) -> 1600 | E10: =SUM(E5:E9) -> 10000 | F10: =E10/10000 -> 1
A11: % del total | B11: =B10/E10 -> 0.5 | C11: =C10/E10 -> 0.34 | D11: =D10/E10 -> 0.16 | E11: 100%
A14: Propuesta de transferencias por parte del PNUD
A15: Transferencia | B15: Momento | C15: Monto (S/) | D15: Justificación
A16: 1.ª transferencia | B16: Al inicio del piloto (firma del acuerdo) | C16: 6000 | D16: 60% del total — para cubrir gastos de arranque (infraestructura, materiales, primeros talleres)
A17: 2.ª transferencia | B17: Tras aprobación del informe de avance (día 30) | C17: 4000 | D17: 40% del total — para cubrir actividades del mes 2-3, evaluación final y cierre

Sheet 8. Contrapartida
A1: CONTRAPARTIDA NO MONETARIA Y ANÁLISIS DE SOSTENIBILIDAD
A2: Esta hoja detalla los aportes no monetarios que multiplican el impacto del Fondo PNUD y la estrategia de sostenibilidad post-piloto. Aunque el presupuesto financiero es de S/ 10 000, el valor total movilizado supera los S/ 30 000 considerando la contrapartida.
A4: Contrapartida no monetaria del equipo
A5: Concepto | B5: Aportante | C5: Detalle | D5: Horas / Cantidad | E5: Valor estimado (S/)
A6: Horas de desarrollo de software | B6: Equipo (4 estudiantes ing. SW/SI) | C6: Desarrollo del backend, frontend y modelo ML | D6: 320 | E6: =D6*25 -> 8000
A7: Horas de gestión y análisis de datos | B7: Estudiante de Ing. Industrial | C7: Análisis de datos, gestión del proyecto, KPIs | D7: 80 | E7: =D7*25 -> 2000
A8: Infraestructura universitaria | B8: UPC / universidades aliadas | C8: Aulas, conectividad, equipos para reuniones | D8: — | E8: 1500
A9: Mentoría académica | B9: Docentes universitarios | C9: Asesoría técnica y metodológica voluntaria | D9: 20 | E9: =D9*80 -> 1600
A10: Difusión institucional | B10: Universidades aliadas | C10: Difusión a través de canales oficiales y bolsas de empleo | D10: — | E10: 1000
A11: Tiempo voluntario de estudiantes | B11: Embajadores PreVe en universidades | C11: Difusión peer-to-peer, registro de usuarios | D11: 200 | E11: =D11*20 -> 4000
A12: TOTAL CONTRAPARTIDA | E12: =SUM(E6:E11) -> 18100
A15: Valor total movilizado por el proyecto
A16: Fondo PNUD (monetario) | B16: 10000
A17: Contrapartida no monetaria | B17: =E12 -> 18100
A18: VALOR TOTAL DEL PROYECTO | B18: =10000+E12 -> 28100
A21: Estrategia de sostenibilidad post-piloto
A22: Vía de sostenibilidad | B22: Descripción
A23: Convenios con universidades | B23: Las universidades aliadas aportan infraestructura y operación a cambio de mejorar la seguridad de su comunidad | E23: 8000
A24: Acuerdos con municipalidades | B24: Pago por acceso a datos agregados anonimizados para serenazgo y patrullaje inteligente | E24: 12000
A25: Fondos concursables | B25: Postulación a Innovate Perú, ProInnóvate, fondos internacionales (BID Lab, Google.org) | E25: 25000
A26: Modelo freemium institucional | B26: Versión básica gratuita; versión premium con dashboards avanzados para gestores municipales | E26: 15000
A27: Patrocinio corporativo (RSE) | B27: Auspicios de empresas tecnológicas y de telecomunicaciones interesadas en RSE | E27: 10000
